cicdhelper/__init__.py
cicdhelper/cicdhelper.py
cicdhelper-0.0.2.dist-info/METADATA
cicdhelper-0.0.2.dist-info/WHEEL
cicdhelper-0.0.2.dist-info/top_level.txt
cicdhelper-0.0.2.dist-info/RECORD
