Metadata-Version: 2.1
Name: cicdhelper
Version: 0.0.2
Requires-Dist: logclshelper
Requires-Dist: syshelper
Requires-Dist: venvhelper
Requires-Dist: ipytopy
Requires-Dist: pytowhl
Requires-Dist: pytopypi
